datadict/__init__.py
datadict/dataclass.py
datadict-1.0.0.dist-info/LICENSE
datadict-1.0.0.dist-info/WHEEL
datadict-1.0.0.dist-info/METADATA
datadict-1.0.0.dist-info/RECORD
