Metadata-Version: 2.1
Name: datadict
Version: 1.0.0
Summary: Add dictionary-like capabilities to dataclasses
Keywords: dataclass,dict,dictionary,item,access
Author-email: Geir Arne Hjelle <geirarne@gmail.com>
Requires-Python: >=3.7
Classifier: Development Status :: 4 - Beta
Classifier: Intended Audience :: Developers
Classifier: License :: OSI Approved :: MIT License
Classifier: Natural Language :: English
Classifier: Operating System :: MacOS
Classifier: Operating System :: Microsoft
Classifier: Operating System :: POSIX :: Linux
Classifier: Programming Language :: Python :: 3.7
Classifier: Programming Language :: Python :: 3.8
Classifier: Programming Language :: Python :: 3.9
Classifier: Programming Language :: Python :: 3.10
Classifier: Programming Language :: Python :: 3.11
Classifier: Topic :: Scientific/Engineering
Classifier: Topic :: Software Development :: Code Generators
Requires-Dist: typing_extensions
Requires-Dist: black ; extra == "dev"
Requires-Dist: bumpversion ; extra == "dev"
Requires-Dist: flake8 ; extra == "dev"
Requires-Dist: flit ; extra == "dev"
Requires-Dist: interrogate ; extra == "dev"
Requires-Dist: isort ; extra == "dev"
Requires-Dist: mypy ; extra == "dev"
Requires-Dist: pre-commit ; extra == "dev"
Requires-Dist: pyright ; extra == "dev"
Requires-Dist: mkdocs ; extra == "doc"
Requires-Dist: black ; extra == "test"
Requires-Dist: flake8 ; extra == "test"
Requires-Dist: interrogate ; extra == "test"
Requires-Dist: isort ; extra == "test"
Requires-Dist: mypy ; extra == "test"
Requires-Dist: pyright ; extra == "test"
Requires-Dist: pytest ; extra == "test"
Requires-Dist: pytest-cov ; extra == "test"
Requires-Dist: tox ; extra == "test"
Project-URL: Homepage, https://github.com/gahjelle/datadict
Provides-Extra: dev
Provides-Extra: doc
Provides-Extra: test
